README.rst
setup.py
plymit/__init__.py
plymit/mesh_ply_types.py
plymit/ply.py
plymit.egg-info/PKG-INFO
plymit.egg-info/SOURCES.txt
plymit.egg-info/dependency_links.txt
plymit.egg-info/not-zip-safe
plymit.egg-info/top_level.txt