Metadata-Version: 1.1
Name: plymit
Version: 1.0.1
Summary: PLY mesh file reader and writer, permissively licensed.
Home-page: http://github.com/MichaelSchoenberg/plymit
Author: Michael Schoenberg
Author-email: michael@michaelschoenberg.com
License: MIT
Keywords: ply mesh
Platform: UNKNOWN
Classifier: Development Status :: 4 - Beta
Classifier: Intended Audience :: Developers
Classifier: Topic :: Multimedia :: Graphics
Classifier: License :: OSI Approved :: MIT License
Classifier: Programming Language :: Python :: 3.5
